<?xml version="1.0" encoding="utf-8" ?>
<dwsync>
<file name="slick.min.js" server="104.130.170.243/vhosts/" local="131287897570000000" remote="131287897570000000" Dst="1" />
<file name="slick-theme.scss" server="104.130.170.243/vhosts/" local="131287897570000000" remote="131287897570000000" Dst="1" />
<file name="slick.js" server="104.130.170.243/vhosts/" local="131287897570000000" remote="131287897570000000" Dst="1" />
<file name="slick.css" server="104.130.170.243/vhosts/" local="131287897570000000" remote="131287897570000000" Dst="1" />
<file name="ajax-loader.gif" server="104.130.170.243/vhosts/" local="131287897570000000" remote="131287897570000000" Dst="1" />
<file name="slick-theme.css" server="104.130.170.243/vhosts/" local="131287897570000000" remote="131287897570000000" Dst="1" />
<file name="slick.scss" server="104.130.170.243/vhosts/" local="131287897570000000" remote="131287897570000000" Dst="1" />
<file name="slick.less" server="104.130.170.243/vhosts/" local="131287897570000000" remote="131287897570000000" Dst="1" />
<file name="slick-theme.less" server="104.130.170.243/vhosts/" local="131287897570000000" remote="131287897570000000" Dst="1" />
<file name="config.rb" server="104.130.170.243/vhosts/" local="131287897570000000" remote="131287897570000000" Dst="1" />
</dwsync>